{"language":"javascript","client_name":"inchjs","args":[],"client_version":"0.4.1","git_repo_url":"git@github.com:tremho/gen-logger.git","branch_name":"master","objects":[{"comment":"*/","meta":{"range":[923,941],"filename":"smx.js","lineno":20,"columnno":6,"path":"/build/smx","code":{"id":"astnode100000003","name":"fs","type":"CallExpression","value":""}},"undocumented":true,"name":"fs","longname":"fs","kind":"constant","scope":"global","params":[]},{"comment":"","meta":{"range":[949,971],"filename":"smx.js","lineno":21,"columnno":6,"path":"/build/smx","code":{"id":"astnode100000009","name":"path","type":"CallExpression","value":""}},"undocumented":true,"name":"path","longname":"path","kind":"constant","scope":"global","params":[]},{"comment":"","meta":{"range":[979,1015],"filename":"smx.js","lineno":22,"columnno":6,"path":"/build/smx","code":{"id":"astnode100000015","name":"smCodec","type":"CallExpression","value":""}},"undocumented":true,"name":"smCodec","longname":"smCodec","kind":"constant","scope":"global","params":[]},{"comment":"","meta":{"range":[1023,1050],"filename":"smx.js","lineno":23,"columnno":6,"path":"/build/smx","code":{"id":"astnode100000021","name":"base64","type":"CallExpression","value":""}},"undocumented":true,"name":"base64","longname":"base64","kind":"constant","scope":"global","params":[]},{"comment":"","meta":{"range":[1098,1225],"filename":"smx.js","lineno":27,"columnno":0,"path":"/build/smx","code":{"id":"astnode100000036","name":"openBundleFile","type":"FunctionDeclaration","paramnames":[]}},"undocumented":true,"name":"openBundleFile","longname":"openBundleFile","kind":"function","scope":"global","params":[]},{"comment":"","meta":{"range":[1226,2368],"filename":"smx.js","lineno":32,"columnno":0,"path":"/build/smx","code":{"id":"astnode100000055","name":"findNextSourceMapEntry","type":"FunctionDeclaration","paramnames":["contents","startPos"]},"vars":{"entryStartTag":"findNextSourceMapEntry~entryStartTag","entryEndTag":"findNextSourceMapEntry~entryEndTag","sourceMapTag":"findNextSourceMapEntry~sourceMapTag","b64Tag":"findNextSourceMapEntry~b64Tag","tagPos":"findNextSourceMapEntry~tagPos","endTagPos":"findNextSourceMapEntry~endTagPos","smTagPos":"findNextSourceMapEntry~smTagPos","startLine":"findNextSourceMapEntry~startLine","endLine":"findNextSourceMapEntry~endLine","eol":"findNextSourceMapEntry~eol","b64":"findNextSourceMapEntry~b64","mapData":"findNextSourceMapEntry~mapData","mapText":"findNextSourceMapEntry~mapText","position":"findNextSourceMapEntry~position"}},"undocumented":true,"name":"findNextSourceMapEntry","longname":"findNextSourceMapEntry","kind":"function","scope":"global","params":[]},{"comment":"","meta":{"range":[2369,2721],"filename":"smx.js","lineno":61,"columnno":0,"path":"/build/smx","code":{"id":"astnode100000216","name":"writeMapInfoFile","type":"FunctionDeclaration","paramnames":[]},"vars":{"mapFile":"writeMapInfoFile~mapFile","infoText":"writeMapInfoFile~infoText","assign":"writeMapInfoFile~assign"}},"undocumented":true,"name":"writeMapInfoFile","longname":"writeMapInfoFile","kind":"function","scope":"global","params":[]},{"comment":"","meta":{"range":[2722,3323],"filename":"smx.js","lineno":73,"columnno":0,"path":"/build/smx","code":{"id":"astnode100000268","name":"makeSourceMap","type":"FunctionDeclaration","paramnames":[]},"vars":{"contents":"makeSourceMap~contents","curPos":"makeSourceMap~curPos","undefined":null,"filename":"makeSourceMap~filename","mapInfo[undefined]":null}},"undocumented":true,"name":"makeSourceMap","longname":"makeSourceMap","kind":"function","scope":"global","params":[]},{"comment":"","meta":{"range":[3330,3349],"filename":"smx.js","lineno":91,"columnno":6,"path":"/build/smx","code":{"id":"astnode100000354","name":"cwd","type":"CallExpression","value":""}},"undocumented":true,"name":"cwd","longname":"cwd","kind":"constant","scope":"global","params":[]},{"comment":"","meta":{"range":[3357,3385],"filename":"smx.js","lineno":92,"columnno":6,"path":"/build/smx","code":{"id":"astnode100000361","name":"bundlePath","type":"MemberExpression","value":"process.argv[2]"}},"undocumented":true,"name":"bundlePath","longname":"bundlePath","kind":"constant","scope":"global","params":[]},{"comment":"","meta":{"range":[1581,1609],"filename":"Configuration.js","lineno":42,"columnno":0,"path":"/build/src","code":{"id":"astnode100000791","name":"CategoryDefinition","type":"ClassDeclaration","paramnames":[]}},"undocumented":true,"name":"CategoryDefinition","longname":"CategoryDefinition","kind":"class","scope":"global"},{"comment":"","meta":{"range":[1659,1776],"filename":"Configuration.js","lineno":45,"columnno":0,"path":"/build/src","code":{"id":"astnode100000800","name":"DisplayOptions","type":"ClassDeclaration","paramnames":[]}},"undocumented":true,"name":"DisplayOptions","longname":"DisplayOptions","kind":"class","scope":"global"},{"comment":"","meta":{"range":[1686,1774],"filename":"Configuration.js","lineno":46,"columnno":4,"path":"/build/src","code":{"id":"astnode100000803","name":"DisplayOptions","type":"MethodDefinition","paramnames":[]},"vars":{"":null}},"undocumented":true,"name":"DisplayOptions","longname":"DisplayOptions","kind":"class","scope":"global","params":[]},{"comment":"","meta":{"range":[1818,1850],"filename":"Configuration.js","lineno":52,"columnno":0,"path":"/build/src","code":{"id":"astnode100000827","name":"ColorElementDefinition","type":"ClassDeclaration","paramnames":[]}},"undocumented":true,"name":"ColorElementDefinition","longname":"ColorElementDefinition","kind":"class","scope":"global"},{"comment":"","meta":{"range":[1908,1960],"filename":"Configuration.js","lineno":55,"columnno":0,"path":"/build/src","code":{"id":"astnode100000836","name":"ColorSchema","type":"ClassDeclaration","paramnames":[]}},"undocumented":true,"name":"ColorSchema","longname":"ColorSchema","kind":"class","scope":"global"},{"comment":"","meta":{"range":[1996,2042],"filename":"Configuration.js","lineno":58,"columnno":0,"path":"/build/src","code":{"id":"astnode100000846","name":"NamedColorScheme","type":"ClassDeclaration","paramnames":[]}},"undocumented":true,"name":"NamedColorScheme","longname":"NamedColorScheme","kind":"class","scope":"global"},{"comment":"","meta":{"range":[2088,2114],"filename":"Configuration.js","lineno":61,"columnno":0,"path":"/build/src","code":{"id":"astnode100000856","name":"WriterDefinition","type":"ClassDeclaration","paramnames":[]}},"undocumented":true,"name":"WriterDefinition","longname":"WriterDefinition","kind":"class","scope":"global"},{"comment":"","meta":{"range":[2160,2186],"filename":"Configuration.js","lineno":64,"columnno":0,"path":"/build/src","code":{"id":"astnode100000865","name":"LoggerDefinition","type":"ClassDeclaration","paramnames":[]}},"undocumented":true,"name":"LoggerDefinition","longname":"LoggerDefinition","kind":"class","scope":"global"},{"comment":"","meta":{"range":[2232,2254],"filename":"Configuration.js","lineno":67,"columnno":0,"path":"/build/src","code":{"id":"astnode100000874","name":"ConfigSchema","type":"ClassDeclaration","paramnames":[]}},"undocumented":true,"name":"ConfigSchema","longname":"ConfigSchema","kind":"class","scope":"global"},{"comment":"","meta":{"range":[2292,3268],"filename":"Configuration.js","lineno":70,"columnno":0,"path":"/build/src","code":{"id":"astnode100000883","name":"Configuration","type":"ClassDeclaration","paramnames":[]}},"undocumented":true,"name":"Configuration","longname":"Configuration","kind":"class","scope":"global"},{"comment":"","meta":{"range":[2318,2698],"filename":"Configuration.js","lineno":71,"columnno":4,"path":"/build/src","code":{"id":"astnode100000886","name":"Configuration#loadConfigFile","type":"MethodDefinition","paramnames":["path"]},"vars":{"":null}},"undocumented":true,"name":"loadConfigFile","longname":"Configuration#loadConfigFile","kind":"function","memberof":"Configuration","scope":"instance","params":[]},{"comment":"","meta":{"range":[2703,3266],"filename":"Configuration.js","lineno":83,"columnno":4,"path":"/build/src","code":{"id":"astnode100000935","name":"Configuration#readColorScheme","type":"MethodDefinition","paramnames":["schemeName"]},"vars":{"":null}},"undocumented":true,"name":"readColorScheme","longname":"Configuration#readColorScheme","kind":"function","memberof":"Configuration","scope":"instance","params":[]},{"comment":"","meta":{"range":[1540,1598],"filename":"Log.js","lineno":36,"columnno":6,"path":"/build/src","code":{"id":"astnode100001299","name":"gen_format_1","type":"CallExpression","value":""}},"undocumented":true,"name":"gen_format_1","longname":"gen_format_1","kind":"constant","scope":"global","params":[]},{"comment":"","meta":{"range":[1606,1664],"filename":"Log.js","lineno":37,"columnno":6,"path":"/build/src","code":{"id":"astnode100001307","name":"Configuration_1","type":"CallExpression","value":""}},"undocumented":true,"name":"Configuration_1","longname":"Configuration_1","kind":"constant","scope":"global","params":[]},{"comment":"","meta":{"range":[1672,1720],"filename":"Log.js","lineno":38,"columnno":6,"path":"/build/src","code":{"id":"astnode100001315","name":"StackLineParser_1","type":"CallExpression","value":""}},"undocumented":true,"name":"StackLineParser_1","longname":"StackLineParser_1","kind":"constant","scope":"global","params":[]},{"comment":"","meta":{"range":[1728,1764],"filename":"Log.js","lineno":39,"columnno":6,"path":"/build/src","code":{"id":"astnode100001321","name":"SourceMap_1","type":"CallExpression","value":""}},"undocumented":true,"name":"SourceMap_1","longname":"SourceMap_1","kind":"constant","scope":"global","params":[]},{"comment":"/**\n* Returns the set of established categories as defined in configuration.\n*/","meta":{"range":[3667,3723],"filename":"Log.js","lineno":98,"columnno":0,"path":"/build/src","code":{"id":"astnode100001338","name":"getCategories","type":"FunctionDeclaration","paramnames":[]}},"description":"Returns the set of established categories as defined in configuration.","name":"getCategories","longname":"getCategories","kind":"function","scope":"global","params":[]},{"comment":"/**\n* Adds a new category to the set of known categories\n* @param category\n*/","meta":{"range":[3805,3875],"filename":"Log.js","lineno":105,"columnno":0,"path":"/build/src","code":{"id":"astnode100001343","name":"addCategory","type":"FunctionDeclaration","paramnames":["category"]}},"description":"Adds a new category to the set of known categories","params":[{"name":"category"}],"name":"addCategory","longname":"addCategory","kind":"function","scope":"global"},{"comment":"/**\n* Removes a category from the set of known categories\n* @param category\n*/","meta":{"range":[3958,4106],"filename":"Log.js","lineno":112,"columnno":0,"path":"/build/src","code":{"id":"astnode100001353","name":"removeCategory","type":"FunctionDeclaration","paramnames":["category"]},"vars":{"n":"removeCategory~n"}},"description":"Removes a category from the set of known categories","params":[{"name":"category"}],"name":"removeCategory","longname":"removeCategory","kind":"function","scope":"global"},{"comment":"/**\n* Loads the logger configuration JSON from the given path and sets the configuration.\n* This establishes the loggers and output writers, as well as category and level\n* definitions, color settings, and output formats to use.\n* See the documentation section on Configuration for more information.\n*\n* Available in Node settings.  For browser-based contexts, load your config\n* via a script or AJAX operation and call `setLoggerConfig` rather than use this method.\n*\n* @throws Error if Node is not available or file is not found at path.\n*\n* @param path\n*/","meta":{"range":[4678,4829],"filename":"Log.js","lineno":131,"columnno":0,"path":"/build/src","code":{"id":"astnode100001378","name":"loadLoggerConfig","type":"FunctionDeclaration","paramnames":["path"]},"vars":{"cfg":"loadLoggerConfig~cfg"}},"description":"Loads the logger configuration JSON from the given path and sets the configuration.\nThis establishes the loggers and output writers, as well as category and level\ndefinitions, color settings, and output formats to use.\nSee the documentation section on Configuration for more information.\n\nAvailable in Node settings.  For browser-based contexts, load your config\nvia a script or AJAX operation and call `setLoggerConfig` rather than use this method.","exceptions":[{"description":"Error if Node is not available or file is not found at path."}],"params":[{"name":"path"}],"name":"loadLoggerConfig","longname":"loadLoggerConfig","kind":"function","scope":"global"},{"comment":"/**\n* Sets the configuration from a JSON text string.\n* If you've loaded a parsed script, or have constructed a JS object,\n* call `setLoggerConfig` instead.\n* @param json\n*/","meta":{"range":[5009,5160],"filename":"Log.js","lineno":142,"columnno":0,"path":"/build/src","code":{"id":"astnode100001401","name":"setLoggerConfigJSON","type":"FunctionDeclaration","paramnames":["json"]},"vars":{"cfg":"setLoggerConfigJSON~cfg","config":"setLoggerConfigJSON~config"}},"description":"Sets the configuration from a JSON text string.\nIf you've loaded a parsed script, or have constructed a JS object,\ncall `setLoggerConfig` instead.","params":[{"name":"json"}],"name":"setLoggerConfigJSON","longname":"setLoggerConfigJSON","kind":"function","scope":"global"},{"comment":"/**\n* Use to set the Logger configuration from an object resolved from JSON or\n* constructed dynamically.\n* Use in browser-based contexts, since `loadLoggerConfig` in unavailable without Node support.\n* This establishes the loggers and output writers, as well as category and level\n* definitions, color settings, and output formats to use.\n* See the documentation section on Configuration for more information.\n* @param config\n*/","meta":{"range":[5599,11094],"filename":"Log.js","lineno":156,"columnno":0,"path":"/build/src","code":{"id":"astnode100001424","name":"setLoggerConfig","type":"FunctionDeclaration","paramnames":["config"]},"vars":{"knownCategories":"setLoggerConfig~knownCategories","i":"setLoggerConfig~i","writers":"setLoggerConfig~writers","writerSet":"setLoggerConfig~writerSet","writer":"setLoggerConfig~writer","location":"setLoggerConfig~location","isColor":"setLoggerConfig~isColor","target":"setLoggerConfig~target","target.supportsColor":"setLoggerConfig~target.supportsColor","target.location":"setLoggerConfig~target.location","target.displayOptions.colorReset":"setLoggerConfig~target.displayOptions.colorReset","levelNames":"setLoggerConfig~levelNames","colors":"setLoggerConfig~colors","cfg":"setLoggerConfig~cfg","cfg.configSchema":"setLoggerConfig~cfg.configSchema","base":"setLoggerConfig~base","target.colorCategories":"setLoggerConfig~target.colorCategories","catName":"setLoggerConfig~catName","target.colorCategories[undefined]":"setLoggerConfig~target.colorCategories[undefined]","target.colorLevels":"setLoggerConfig~target.colorLevels","lvlName":"setLoggerConfig~lvlName","target.colorLevels[undefined]":"setLoggerConfig~target.colorLevels[undefined]","n":"setLoggerConfig~n","target.displayOptions.format":"setLoggerConfig~target.displayOptions.format","target.displayOptions.order":"setLoggerConfig~target.displayOptions.order","writerSet[undefined]":"setLoggerConfig~writerSet.undefined]","definedLoggers":"setLoggerConfig~definedLoggers","loggers":"setLoggerConfig~loggers","logger":"setLoggerConfig~logger","lgr":"setLoggerConfig~lgr","lgrwrts":"setLoggerConfig~lgrwrts","lgwrt":"setLoggerConfig~lgwrt","definedLoggers[undefined]":"setLoggerConfig~definedLoggers[undefined]"}},"description":"Use to set the Logger configuration from an object resolved from JSON or\nconstructed dynamically.\nUse in browser-based contexts, since `loadLoggerConfig` in unavailable without Node support.\nThis establishes the loggers and output writers, as well as category and level\ndefinitions, color settings, and output formats to use.\nSee the documentation section on Configuration for more information.","params":[{"name":"config"}],"name":"setLoggerConfig","longname":"setLoggerConfig","kind":"function","scope":"global"},{"comment":"/**\n* Return a configured Logger by name\n* @param name\n*/","meta":{"range":[11156,11327],"filename":"Log.js","lineno":287,"columnno":0,"path":"/build/src","code":{"id":"astnode100002073","name":"getLogger","type":"FunctionDeclaration","paramnames":["name"]},"vars":{"logger":"getLogger~logger"}},"description":"Return a configured Logger by name","params":[{"name":"name"}],"name":"getLogger","longname":"getLogger","kind":"function","scope":"global"},{"comment":"/**\n* Read the accumulated text in the named memory log.\n* Note that the name of a Memory log is established with the 'memoryName' property of\n* the writer configuration, or the name of the writer itself if no 'memoryName' is provided.\n* See the section on Configuration for more info.\n*\n* @param name\n*/","meta":{"range":[11640,11703],"filename":"Log.js","lineno":302,"columnno":0,"path":"/build/src","code":{"id":"astnode100002097","name":"readMemoryLog","type":"FunctionDeclaration","paramnames":["name"]}},"description":"Read the accumulated text in the named memory log.\nNote that the name of a Memory log is established with the 'memoryName' property of\nthe writer configuration, or the name of the writer itself if no 'memoryName' is provided.\nSee the section on Configuration for more info.","params":[{"name":"name"}],"name":"readMemoryLog","longname":"readMemoryLog","kind":"function","scope":"global"},{"comment":"/**\n* Clears the memory buffer text for this Memory log.\n* @param name\n*/","meta":{"range":[11781,11843],"filename":"Log.js","lineno":309,"columnno":0,"path":"/build/src","code":{"id":"astnode100002105","name":"clearMemoryLog","type":"FunctionDeclaration","paramnames":["name"]},"vars":{"memoryCaches[undefined]":null}},"description":"Clears the memory buffer text for this Memory log.","params":[{"name":"name"}],"name":"clearMemoryLog","longname":"clearMemoryLog","kind":"function","scope":"global"},{"comment":"/**\n* A target names the target type and location\n*/","meta":{"range":[12859,13755],"filename":"Log.js","lineno":360,"columnno":0,"path":"/build/src","code":{"id":"astnode100002115","name":"LogTarget","type":"ClassDeclaration","paramnames":["name","type","location","color"]}},"classdesc":"A target names the target type and location","name":"LogTarget","longname":"LogTarget","kind":"class","scope":"global","undocumented":true},{"comment":"","meta":{"range":[12881,13753],"filename":"Log.js","lineno":361,"columnno":4,"path":"/build/src","code":{"id":"astnode100002118","name":"LogTarget","type":"MethodDefinition","paramnames":["name","type","location","color"]},"vars":{"":null}},"undocumented":true,"name":"LogTarget","longname":"LogTarget","kind":"class","scope":"global","params":[]},{"comment":"/**\n* A target names the target type and location\n*/","meta":{"range":[12859,13755],"filename":"Log.js","lineno":360,"columnno":0,"path":"/build/src","code":{"id":"astnode100002115","name":"LogTarget","type":"ClassDeclaration","paramnames":["name","type","location","color"]}},"name":"LogTarget","longname":"LogTarget","kind":"class","classdesc":"A target names the target type and location","scope":"global"},{"comment":"/**\n* Defines where the output will appear, and what categories/levels are filtered\n*/","meta":{"range":[13876,27406],"filename":"Log.js","lineno":382,"columnno":0,"path":"/build/src","code":{"id":"astnode100002234","name":"LogWriter","type":"ClassDeclaration","paramnames":["target"]}},"classdesc":"Defines where the output will appear, and what categories/levels are filtered","name":"LogWriter","longname":"LogWriter","kind":"class","scope":"global","undocumented":true},{"comment":"","meta":{"range":[13898,14024],"filename":"Log.js","lineno":383,"columnno":4,"path":"/build/src","code":{"id":"astnode100002237","name":"LogWriter","type":"MethodDefinition","paramnames":["target"]},"vars":{"":null}},"undocumented":true,"name":"LogWriter","longname":"LogWriter","kind":"class","scope":"global","params":[]},{"comment":"/**\n* Defines where the output will appear, and what categories/levels are filtered\n*/","meta":{"range":[13876,27406],"filename":"Log.js","lineno":382,"columnno":0,"path":"/build/src","code":{"id":"astnode100002234","name":"LogWriter","type":"ClassDeclaration","paramnames":["target"]}},"name":"LogWriter","longname":"LogWriter","kind":"class","classdesc":"Defines where the output will appear, and what categories/levels are filtered","scope":"global"},{"comment":"","meta":{"range":[14029,14367],"filename":"Log.js","lineno":388,"columnno":4,"path":"/build/src","code":{"id":"astnode100002260","name":"LogWriter#includeCategory","type":"MethodDefinition","paramnames":["category","more"]},"vars":{"":null}},"undocumented":true,"name":"includeCategory","longname":"LogWriter#includeCategory","kind":"function","memberof":"LogWriter","scope":"instance","params":[]},{"comment":"","meta":{"range":[14372,14693],"filename":"Log.js","lineno":399,"columnno":4,"path":"/build/src","code":{"id":"astnode100002316","name":"LogWriter#excludeCategory","type":"MethodDefinition","paramnames":["category","more"]},"vars":{"":null}},"undocumented":true,"name":"excludeCategory","longname":"LogWriter#excludeCategory","kind":"function","memberof":"LogWriter","scope":"instance","params":[]},{"comment":"","meta":{"range":[14698,15018],"filename":"Log.js","lineno":409,"columnno":4,"path":"/build/src","code":{"id":"astnode100002367","name":"LogWriter#includeLevel","type":"MethodDefinition","paramnames":["level","more"]},"vars":{"":null}},"undocumented":true,"name":"includeLevel","longname":"LogWriter#includeLevel","kind":"function","memberof":"LogWriter","scope":"instance","params":[]},{"comment":"","meta":{"range":[15023,15323],"filename":"Log.js","lineno":420,"columnno":4,"path":"/build/src","code":{"id":"astnode100002423","name":"LogWriter#excludeLevel","type":"MethodDefinition","paramnames":["level","more"]},"vars":{"":null}},"undocumented":true,"name":"excludeLevel","longname":"LogWriter#excludeLevel","kind":"function","memberof":"LogWriter","scope":"instance","params":[]},{"comment":"","meta":{"range":[15328,15427],"filename":"Log.js","lineno":430,"columnno":4,"path":"/build/src","code":{"id":"astnode100002474","name":"LogWriter#isCategoryExcluded","type":"MethodDefinition","paramnames":["category"]},"vars":{"":null}},"undocumented":true,"name":"isCategoryExcluded","longname":"LogWriter#isCategoryExcluded","kind":"function","memberof":"LogWriter","scope":"instance","params":[]},{"comment":"","meta":{"range":[15432,15625],"filename":"Log.js","lineno":433,"columnno":4,"path":"/build/src","code":{"id":"astnode100002490","name":"LogWriter#isLevelExcluded","type":"MethodDefinition","paramnames":["level"]},"vars":{"":null}},"undocumented":true,"name":"isLevelExcluded","longname":"LogWriter#isLevelExcluded","kind":"function","memberof":"LogWriter","scope":"instance","params":[]},{"comment":"","meta":{"range":[15630,16988],"filename":"Log.js","lineno":437,"columnno":4,"path":"/build/src","code":{"id":"astnode100002530","name":"LogWriter#outputLog","type":"MethodDefinition","paramnames":["formatted","category","level","stack","xargs"]},"vars":{"":null}},"undocumented":true,"name":"outputLog","longname":"LogWriter#outputLog","kind":"function","memberof":"LogWriter","scope":"instance","params":[]},{"comment":"","meta":{"range":[16993,17736],"filename":"Log.js","lineno":471,"columnno":4,"path":"/build/src","code":{"id":"astnode100002680","name":"LogWriter#startGroup","type":"MethodDefinition","paramnames":["indent","groupName"]},"vars":{"":null}},"undocumented":true,"name":"startGroup","longname":"LogWriter#startGroup","kind":"function","memberof":"LogWriter","scope":"instance","params":[]},{"comment":"","meta":{"range":[17741,18438],"filename":"Log.js","lineno":486,"columnno":4,"path":"/build/src","code":{"id":"astnode100002794","name":"LogWriter#endGroup","type":"MethodDefinition","paramnames":["indent","groupName"]},"vars":{"":null}},"undocumented":true,"name":"endGroup","longname":"LogWriter#endGroup","kind":"function","memberof":"LogWriter","scope":"instance","params":[]},{"comment":"/**\n* Returns the colors to use per display item for a given category and level\n* @param category\n* @param level\n* @returns Object containing color info\n*/","meta":{"range":[18628,20112],"filename":"Log.js","lineno":507,"columnno":4,"path":"/build/src","code":{"id":"astnode100002900","name":"LogWriter#getColors","type":"MethodDefinition","paramnames":["category","level"]},"vars":{"":null}},"description":"Returns the colors to use per display item for a given category and level","params":[{"name":"category"},{"name":"level"}],"returns":[{"description":"Object containing color info"}],"name":"getColors","longname":"LogWriter#getColors","kind":"function","memberof":"LogWriter","scope":"instance"},{"comment":"/**\n* Support output as JSON\n*/","meta":{"range":[20163,20873],"filename":"Log.js","lineno":529,"columnno":4,"path":"/build/src","code":{"id":"astnode100003189","name":"LogWriter#composeJSON","type":"MethodDefinition","paramnames":["time","category","level","ffl","fmesg","stackdump"]},"vars":{"":null}},"description":"Support output as JSON","name":"composeJSON","longname":"LogWriter#composeJSON","kind":"function","memberof":"LogWriter","scope":"instance","params":[]},{"comment":"/**\n* Format the log output\n*/","meta":{"range":[20923,27404],"filename":"Log.js","lineno":551,"columnno":4,"path":"/build/src","code":{"id":"astnode100003329","name":"LogWriter#logFormat","type":"MethodDefinition","paramnames":["time","category","level","ffl","stackParser","message","args"]},"vars":{"":null}},"description":"Format the log output","name":"logFormat","longname":"LogWriter#logFormat","kind":"function","memberof":"LogWriter","scope":"instance","params":[]},{"comment":"","meta":{"range":[27438,38943],"filename":"Log.js","lineno":705,"columnno":0,"path":"/build/src","code":{"id":"astnode100004229","name":"Logger","type":"ClassDeclaration","paramnames":[]}},"undocumented":true,"name":"Logger","longname":"Logger","kind":"class","scope":"global"},{"comment":"","meta":{"range":[27457,27599],"filename":"Log.js","lineno":706,"columnno":4,"path":"/build/src","code":{"id":"astnode100004232","name":"Logger","type":"MethodDefinition","paramnames":[]},"vars":{"":null}},"undocumented":true,"name":"Logger","longname":"Logger","kind":"class","scope":"global","params":[]},{"comment":"/**\n* return the array of writers attached to this logger\n*/","meta":{"range":[27679,27728],"filename":"Log.js","lineno":714,"columnno":4,"path":"/build/src","code":{"id":"astnode100004257","name":"Logger#getWriters","type":"MethodDefinition","paramnames":[]},"vars":{"":null}},"description":"return the array of writers attached to this logger","name":"getWriters","longname":"Logger#getWriters","kind":"function","memberof":"Logger","scope":"instance","params":[]},{"comment":"/**\n* Add a new writer to this logger\n* @param writer\n*/","meta":{"range":[27809,27935],"filename":"Log.js","lineno":721,"columnno":4,"path":"/build/src","code":{"id":"astnode100004265","name":"Logger#addWriter","type":"MethodDefinition","paramnames":["writer"]},"vars":{"":null}},"description":"Add a new writer to this logger","params":[{"name":"writer"}],"name":"addWriter","longname":"Logger#addWriter","kind":"function","memberof":"Logger","scope":"instance"},{"comment":"/**\n* Remove a writer from this logger\n* @param writer\n*/","meta":{"range":[28017,28326],"filename":"Log.js","lineno":730,"columnno":4,"path":"/build/src","code":{"id":"astnode100004290","name":"Logger#removeWriter","type":"MethodDefinition","paramnames":["writer"]},"vars":{"":null}},"description":"Remove a writer from this logger","params":[{"name":"writer"}],"name":"removeWriter","longname":"Logger#removeWriter","kind":"function","memberof":"Logger","scope":"instance"},{"comment":"/**\n* Find a writer by name that belongs to this Logger\n* @param targetName\n*/","meta":{"range":[28429,28676],"filename":"Log.js","lineno":744,"columnno":4,"path":"/build/src","code":{"id":"astnode100004345","name":"Logger#findWriter","type":"MethodDefinition","paramnames":["targetName"]},"vars":{"":null}},"description":"Find a writer by name that belongs to this Logger","params":[{"name":"targetName"}],"name":"findWriter","longname":"Logger#findWriter","kind":"function","memberof":"Logger","scope":"instance"},{"comment":"/**\n* Private method that converts a string 'level' (e.g. 'info', 'debug3', etc)\n* into the corresponding type (number) and suffix granularity.\n* @param level\n* @returns {{type, granularity}) (both properties are integers)\n* @private\n*/","meta":{"range":[28952,29315],"filename":"Log.js","lineno":760,"columnno":4,"path":"/build/src","code":{"id":"astnode100004386","name":"Logger#_levelToType","type":"MethodDefinition","paramnames":["level"]},"vars":{"":null}},"description":"Private method that converts a string 'level' (e.g. 'info', 'debug3', etc)\ninto the corresponding type (number) and suffix granularity.","params":[{"name":"level"}],"returns":[{"description":"{{type, granularity}) (both properties are integers)"}],"access":"private","name":"_levelToType","longname":"Logger#_levelToType","kind":"function","memberof":"Logger","scope":"instance"},{"comment":"/**\n* Direct output to all writers, subject to filtering.\n* @param {number} time  in milliseconds\n* @param {{file, func, line, stack}} ffl\n* @param {string} category\n* @param {string} level\n* @param {string} message\n* @param {*} args arguments used for formatting message\n*/","meta":{"range":[29639,30858],"filename":"Log.js","lineno":782,"columnno":4,"path":"/build/src","code":{"id":"astnode100004455","name":"Logger#outToWriters","type":"MethodDefinition","paramnames":["time","ffl","category","level","message","args"]},"vars":{"":null}},"description":"Direct output to all writers, subject to filtering.","params":[{"type":{"names":["number"]},"description":"in milliseconds","name":"time"},{"type":{"names":["Object"]},"name":"ffl"},{"type":{"names":["string"]},"name":"category"},{"type":{"names":["string"]},"name":"level"},{"type":{"names":["string"]},"name":"message"},{"type":{"names":["*"]},"description":"arguments used for formatting message","name":"args","variable":true}],"name":"outToWriters","longname":"Logger#outToWriters","kind":"function","memberof":"Logger","scope":"instance"},{"comment":"/**\n* Handles passing category, message, args or simply message, args for any log level.\n* @param level\n* @param args\n* @private\n*/","meta":{"range":[31024,32188],"filename":"Log.js","lineno":812,"columnno":4,"path":"/build/src","code":{"id":"astnode100004580","name":"Logger#_morph","type":"MethodDefinition","paramnames":["level","args"]},"vars":{"":null}},"description":"Handles passing category, message, args or simply message, args for any log level.","params":[{"name":"level"},{"name":"args","variable":true}],"access":"private","name":"_morph","longname":"Logger#_morph","kind":"function","memberof":"Logger","scope":"instance"},{"comment":"/** Outputs log at the named level granularity */","meta":{"range":[32247,32310],"filename":"Log.js","lineno":846,"columnno":4,"path":"/build/src","code":{"id":"astnode100004708","name":"Logger#debug9","type":"MethodDefinition","paramnames":["args"]},"vars":{"":null}},"description":"Outputs log at the named level granularity","name":"debug9","longname":"Logger#debug9","kind":"function","memberof":"Logger","scope":"instance","params":[]},{"comment":"/** Outputs log at the named level granularity */","meta":{"range":[32369,32432],"filename":"Log.js","lineno":850,"columnno":4,"path":"/build/src","code":{"id":"astnode100004722","name":"Logger#debug8","type":"MethodDefinition","paramnames":["args"]},"vars":{"":null}},"description":"Outputs log at the named level granularity","name":"debug8","longname":"Logger#debug8","kind":"function","memberof":"Logger","scope":"instance","params":[]},{"comment":"/** Outputs log at the named level granularity */","meta":{"range":[32491,32554],"filename":"Log.js","lineno":854,"columnno":4,"path":"/build/src","code":{"id":"astnode100004736","name":"Logger#debug7","type":"MethodDefinition","paramnames":["args"]},"vars":{"":null}},"description":"Outputs log at the named level granularity","name":"debug7","longname":"Logger#debug7","kind":"function","memberof":"Logger","scope":"instance","params":[]},{"comment":"/** Outputs log at the named level granularity */","meta":{"range":[32613,32676],"filename":"Log.js","lineno":858,"columnno":4,"path":"/build/src","code":{"id":"astnode100004750","name":"Logger#debug6","type":"MethodDefinition","paramnames":["args"]},"vars":{"":null}},"description":"Outputs log at the named level granularity","name":"debug6","longname":"Logger#debug6","kind":"function","memberof":"Logger","scope":"instance","params":[]},{"comment":"/** Outputs log at the named level granularity */","meta":{"range":[32735,32798],"filename":"Log.js","lineno":862,"columnno":4,"path":"/build/src","code":{"id":"astnode100004764","name":"Logger#debug5","type":"MethodDefinition","paramnames":["args"]},"vars":{"":null}},"description":"Outputs log at the named level granularity","name":"debug5","longname":"Logger#debug5","kind":"function","memberof":"Logger","scope":"instance","params":[]},{"comment":"/** Outputs log at the named level granularity */","meta":{"range":[32857,32920],"filename":"Log.js","lineno":866,"columnno":4,"path":"/build/src","code":{"id":"astnode100004778","name":"Logger#debug4","type":"MethodDefinition","paramnames":["args"]},"vars":{"":null}},"description":"Outputs log at the named level granularity","name":"debug4","longname":"Logger#debug4","kind":"function","memberof":"Logger","scope":"instance","params":[]},{"comment":"/** Outputs log at the named level granularity */","meta":{"range":[32979,33042],"filename":"Log.js","lineno":870,"columnno":4,"path":"/build/src","code":{"id":"astnode100004792","name":"Logger#debug3","type":"MethodDefinition","paramnames":["args"]},"vars":{"":null}},"description":"Outputs log at the named level granularity","name":"debug3","longname":"Logger#debug3","kind":"function","memberof":"Logger","scope":"instance","params":[]},{"comment":"/** Outputs log at the named level granularity */","meta":{"range":[33101,33164],"filename":"Log.js","lineno":874,"columnno":4,"path":"/build/src","code":{"id":"astnode100004806","name":"Logger#debug2","type":"MethodDefinition","paramnames":["args"]},"vars":{"":null}},"description":"Outputs log at the named level granularity","name":"debug2","longname":"Logger#debug2","kind":"function","memberof":"Logger","scope":"instance","params":[]},{"comment":"/** Outputs log at the named level granularity */","meta":{"range":[33223,33286],"filename":"Log.js","lineno":878,"columnno":4,"path":"/build/src","code":{"id":"astnode100004820","name":"Logger#debug1","type":"MethodDefinition","paramnames":["args"]},"vars":{"":null}},"description":"Outputs log at the named level granularity","name":"debug1","longname":"Logger#debug1","kind":"function","memberof":"Logger","scope":"instance","params":[]},{"comment":"/** Outputs log at the named level granularity */","meta":{"range":[33345,33408],"filename":"Log.js","lineno":882,"columnno":4,"path":"/build/src","code":{"id":"astnode100004834","name":"Logger#debug0","type":"MethodDefinition","paramnames":["args"]},"vars":{"":null}},"description":"Outputs log at the named level granularity","name":"debug0","longname":"Logger#debug0","kind":"function","memberof":"Logger","scope":"instance","params":[]},{"comment":"/** Synonymous with debug0 */","meta":{"range":[33447,33499],"filename":"Log.js","lineno":886,"columnno":4,"path":"/build/src","code":{"id":"astnode100004848","name":"Logger#debug","type":"MethodDefinition","paramnames":["args"]},"vars":{"":null}},"description":"Synonymous with debug0","name":"debug","longname":"Logger#debug","kind":"function","memberof":"Logger","scope":"instance","params":[]},{"comment":"/** Outputs log at the named level granularity */","meta":{"range":[33558,33617],"filename":"Log.js","lineno":890,"columnno":4,"path":"/build/src","code":{"id":"astnode100004861","name":"Logger#log9","type":"MethodDefinition","paramnames":["args"]},"vars":{"":null}},"description":"Outputs log at the named level granularity","name":"log9","longname":"Logger#log9","kind":"function","memberof":"Logger","scope":"instance","params":[]},{"comment":"/** Outputs log at the named level granularity */","meta":{"range":[33676,33735],"filename":"Log.js","lineno":894,"columnno":4,"path":"/build/src","code":{"id":"astnode100004875","name":"Logger#log8","type":"MethodDefinition","paramnames":["args"]},"vars":{"":null}},"description":"Outputs log at the named level granularity","name":"log8","longname":"Logger#log8","kind":"function","memberof":"Logger","scope":"instance","params":[]},{"comment":"/** Outputs log at the named level granularity */","meta":{"range":[33794,33853],"filename":"Log.js","lineno":898,"columnno":4,"path":"/build/src","code":{"id":"astnode100004889","name":"Logger#log7","type":"MethodDefinition","paramnames":["args"]},"vars":{"":null}},"description":"Outputs log at the named level granularity","name":"log7","longname":"Logger#log7","kind":"function","memberof":"Logger","scope":"instance","params":[]},{"comment":"/** Outputs log at the named level granularity */","meta":{"range":[33912,33971],"filename":"Log.js","lineno":902,"columnno":4,"path":"/build/src","code":{"id":"astnode100004903","name":"Logger#log6","type":"MethodDefinition","paramnames":["args"]},"vars":{"":null}},"description":"Outputs log at the named level granularity","name":"log6","longname":"Logger#log6","kind":"function","memberof":"Logger","scope":"instance","params":[]},{"comment":"/** Outputs log at the named level granularity */","meta":{"range":[34030,34089],"filename":"Log.js","lineno":906,"columnno":4,"path":"/build/src","code":{"id":"astnode100004917","name":"Logger#log5","type":"MethodDefinition","paramnames":["args"]},"vars":{"":null}},"description":"Outputs log at the named level granularity","name":"log5","longname":"Logger#log5","kind":"function","memberof":"Logger","scope":"instance","params":[]},{"comment":"/** Outputs log at the named level granularity */","meta":{"range":[34148,34207],"filename":"Log.js","lineno":910,"columnno":4,"path":"/build/src","code":{"id":"astnode100004931","name":"Logger#log4","type":"MethodDefinition","paramnames":["args"]},"vars":{"":null}},"description":"Outputs log at the named level granularity","name":"log4","longname":"Logger#log4","kind":"function","memberof":"Logger","scope":"instance","params":[]},{"comment":"/** Outputs log at the named level granularity */","meta":{"range":[34266,34325],"filename":"Log.js","lineno":914,"columnno":4,"path":"/build/src","code":{"id":"astnode100004945","name":"Logger#log3","type":"MethodDefinition","paramnames":["args"]},"vars":{"":null}},"description":"Outputs log at the named level granularity","name":"log3","longname":"Logger#log3","kind":"function","memberof":"Logger","scope":"instance","params":[]},{"comment":"/** Outputs log at the named level granularity */","meta":{"range":[34384,34443],"filename":"Log.js","lineno":918,"columnno":4,"path":"/build/src","code":{"id":"astnode100004959","name":"Logger#log2","type":"MethodDefinition","paramnames":["args"]},"vars":{"":null}},"description":"Outputs log at the named level granularity","name":"log2","longname":"Logger#log2","kind":"function","memberof":"Logger","scope":"instance","params":[]},{"comment":"/** Outputs log at the named level granularity */","meta":{"range":[34502,34561],"filename":"Log.js","lineno":922,"columnno":4,"path":"/build/src","code":{"id":"astnode100004973","name":"Logger#log1","type":"MethodDefinition","paramnames":["args"]},"vars":{"":null}},"description":"Outputs log at the named level granularity","name":"log1","longname":"Logger#log1","kind":"function","memberof":"Logger","scope":"instance","params":[]},{"comment":"/** Outputs log at the named level granularity */","meta":{"range":[34620,34679],"filename":"Log.js","lineno":926,"columnno":4,"path":"/build/src","code":{"id":"astnode100004987","name":"Logger#log0","type":"MethodDefinition","paramnames":["args"]},"vars":{"":null}},"description":"Outputs log at the named level granularity","name":"log0","longname":"Logger#log0","kind":"function","memberof":"Logger","scope":"instance","params":[]},{"comment":"/** Synonymous with log0 */","meta":{"range":[34716,34764],"filename":"Log.js","lineno":930,"columnno":4,"path":"/build/src","code":{"id":"astnode100005001","name":"Logger#log","type":"MethodDefinition","paramnames":["args"]},"vars":{"":null}},"description":"Synonymous with log0","name":"log","longname":"Logger#log","kind":"function","memberof":"Logger","scope":"instance","params":[]},{"comment":"/** Outputs log at the named level granularity */","meta":{"range":[34823,34884],"filename":"Log.js","lineno":934,"columnno":4,"path":"/build/src","code":{"id":"astnode100005014","name":"Logger#info9","type":"MethodDefinition","paramnames":["args"]},"vars":{"":null}},"description":"Outputs log at the named level granularity","name":"info9","longname":"Logger#info9","kind":"function","memberof":"Logger","scope":"instance","params":[]},{"comment":"/** Outputs log at the named level granularity */","meta":{"range":[34943,35004],"filename":"Log.js","lineno":938,"columnno":4,"path":"/build/src","code":{"id":"astnode100005028","name":"Logger#info8","type":"MethodDefinition","paramnames":["args"]},"vars":{"":null}},"description":"Outputs log at the named level granularity","name":"info8","longname":"Logger#info8","kind":"function","memberof":"Logger","scope":"instance","params":[]},{"comment":"/** Outputs log at the named level granularity */","meta":{"range":[35063,35124],"filename":"Log.js","lineno":942,"columnno":4,"path":"/build/src","code":{"id":"astnode100005042","name":"Logger#info7","type":"MethodDefinition","paramnames":["args"]},"vars":{"":null}},"description":"Outputs log at the named level granularity","name":"info7","longname":"Logger#info7","kind":"function","memberof":"Logger","scope":"instance","params":[]},{"comment":"/** Outputs log at the named level granularity */","meta":{"range":[35183,35244],"filename":"Log.js","lineno":946,"columnno":4,"path":"/build/src","code":{"id":"astnode100005056","name":"Logger#info6","type":"MethodDefinition","paramnames":["args"]},"vars":{"":null}},"description":"Outputs log at the named level granularity","name":"info6","longname":"Logger#info6","kind":"function","memberof":"Logger","scope":"instance","params":[]},{"comment":"/** Outputs log at the named level granularity */","meta":{"range":[35303,35364],"filename":"Log.js","lineno":950,"columnno":4,"path":"/build/src","code":{"id":"astnode100005070","name":"Logger#info5","type":"MethodDefinition","paramnames":["args"]},"vars":{"":null}},"description":"Outputs log at the named level granularity","name":"info5","longname":"Logger#info5","kind":"function","memberof":"Logger","scope":"instance","params":[]},{"comment":"/** Outputs log at the named level granularity */","meta":{"range":[35423,35484],"filename":"Log.js","lineno":954,"columnno":4,"path":"/build/src","code":{"id":"astnode100005084","name":"Logger#info4","type":"MethodDefinition","paramnames":["args"]},"vars":{"":null}},"description":"Outputs log at the named level granularity","name":"info4","longname":"Logger#info4","kind":"function","memberof":"Logger","scope":"instance","params":[]},{"comment":"/** Outputs log at the named level granularity */","meta":{"range":[35543,35604],"filename":"Log.js","lineno":958,"columnno":4,"path":"/build/src","code":{"id":"astnode100005098","name":"Logger#info3","type":"MethodDefinition","paramnames":["args"]},"vars":{"":null}},"description":"Outputs log at the named level granularity","name":"info3","longname":"Logger#info3","kind":"function","memberof":"Logger","scope":"instance","params":[]},{"comment":"/** Outputs log at the named level granularity */","meta":{"range":[35663,35724],"filename":"Log.js","lineno":962,"columnno":4,"path":"/build/src","code":{"id":"astnode100005112","name":"Logger#info2","type":"MethodDefinition","paramnames":["args"]},"vars":{"":null}},"description":"Outputs log at the named level granularity","name":"info2","longname":"Logger#info2","kind":"function","memberof":"Logger","scope":"instance","params":[]},{"comment":"/** Outputs log at the named level granularity */","meta":{"range":[35783,35844],"filename":"Log.js","lineno":966,"columnno":4,"path":"/build/src","code":{"id":"astnode100005126","name":"Logger#info1","type":"MethodDefinition","paramnames":["args"]},"vars":{"":null}},"description":"Outputs log at the named level granularity","name":"info1","longname":"Logger#info1","kind":"function","memberof":"Logger","scope":"instance","params":[]},{"comment":"/** Outputs log at the named level granularity */","meta":{"range":[35903,35964],"filename":"Log.js","lineno":970,"columnno":4,"path":"/build/src","code":{"id":"astnode100005140","name":"Logger#info0","type":"MethodDefinition","paramnames":["args"]},"vars":{"":null}},"description":"Outputs log at the named level granularity","name":"info0","longname":"Logger#info0","kind":"function","memberof":"Logger","scope":"instance","params":[]},{"comment":"/** Synonymous with info0 */","meta":{"range":[36002,36052],"filename":"Log.js","lineno":974,"columnno":4,"path":"/build/src","code":{"id":"astnode100005154","name":"Logger#info","type":"MethodDefinition","paramnames":["args"]},"vars":{"":null}},"description":"Synonymous with info0","name":"info","longname":"Logger#info","kind":"function","memberof":"Logger","scope":"instance","params":[]},{"comment":"/** Outputs log at the named level granularity */","meta":{"range":[36111,36172],"filename":"Log.js","lineno":978,"columnno":4,"path":"/build/src","code":{"id":"astnode100005167","name":"Logger#warn9","type":"MethodDefinition","paramnames":["args"]},"vars":{"":null}},"description":"Outputs log at the named level granularity","name":"warn9","longname":"Logger#warn9","kind":"function","memberof":"Logger","scope":"instance","params":[]},{"comment":"/** Outputs log at the named level granularity */","meta":{"range":[36231,36292],"filename":"Log.js","lineno":982,"columnno":4,"path":"/build/src","code":{"id":"astnode100005181","name":"Logger#warn8","type":"MethodDefinition","paramnames":["args"]},"vars":{"":null}},"description":"Outputs log at the named level granularity","name":"warn8","longname":"Logger#warn8","kind":"function","memberof":"Logger","scope":"instance","params":[]},{"comment":"/** Outputs log at the named level granularity */","meta":{"range":[36351,36412],"filename":"Log.js","lineno":986,"columnno":4,"path":"/build/src","code":{"id":"astnode100005195","name":"Logger#warn7","type":"MethodDefinition","paramnames":["args"]},"vars":{"":null}},"description":"Outputs log at the named level granularity","name":"warn7","longname":"Logger#warn7","kind":"function","memberof":"Logger","scope":"instance","params":[]},{"comment":"/** Outputs log at the named level granularity */","meta":{"range":[36471,36532],"filename":"Log.js","lineno":990,"columnno":4,"path":"/build/src","code":{"id":"astnode100005209","name":"Logger#warn6","type":"MethodDefinition","paramnames":["args"]},"vars":{"":null}},"description":"Outputs log at the named level granularity","name":"warn6","longname":"Logger#warn6","kind":"function","memberof":"Logger","scope":"instance","params":[]},{"comment":"/** Outputs log at the named level granularity */","meta":{"range":[36591,36652],"filename":"Log.js","lineno":994,"columnno":4,"path":"/build/src","code":{"id":"astnode100005223","name":"Logger#warn5","type":"MethodDefinition","paramnames":["args"]},"vars":{"":null}},"description":"Outputs log at the named level granularity","name":"warn5","longname":"Logger#warn5","kind":"function","memberof":"Logger","scope":"instance","params":[]},{"comment":"/** Outputs log at the named level granularity */","meta":{"range":[36711,36772],"filename":"Log.js","lineno":998,"columnno":4,"path":"/build/src","code":{"id":"astnode100005237","name":"Logger#warn4","type":"MethodDefinition","paramnames":["args"]},"vars":{"":null}},"description":"Outputs log at the named level granularity","name":"warn4","longname":"Logger#warn4","kind":"function","memberof":"Logger","scope":"instance","params":[]},{"comment":"/** Outputs log at the named level granularity */","meta":{"range":[36831,36892],"filename":"Log.js","lineno":1002,"columnno":4,"path":"/build/src","code":{"id":"astnode100005251","name":"Logger#warn3","type":"MethodDefinition","paramnames":["args"]},"vars":{"":null}},"description":"Outputs log at the named level granularity","name":"warn3","longname":"Logger#warn3","kind":"function","memberof":"Logger","scope":"instance","params":[]},{"comment":"/** Outputs log at the named level granularity */","meta":{"range":[36951,37012],"filename":"Log.js","lineno":1006,"columnno":4,"path":"/build/src","code":{"id":"astnode100005265","name":"Logger#warn2","type":"MethodDefinition","paramnames":["args"]},"vars":{"":null}},"description":"Outputs log at the named level granularity","name":"warn2","longname":"Logger#warn2","kind":"function","memberof":"Logger","scope":"instance","params":[]},{"comment":"/** Outputs log at the named level granularity */","meta":{"range":[37071,37132],"filename":"Log.js","lineno":1010,"columnno":4,"path":"/build/src","code":{"id":"astnode100005279","name":"Logger#warn1","type":"MethodDefinition","paramnames":["args"]},"vars":{"":null}},"description":"Outputs log at the named level granularity","name":"warn1","longname":"Logger#warn1","kind":"function","memberof":"Logger","scope":"instance","params":[]},{"comment":"/** Outputs log at the named level granularity */","meta":{"range":[37191,37252],"filename":"Log.js","lineno":1014,"columnno":4,"path":"/build/src","code":{"id":"astnode100005293","name":"Logger#warn0","type":"MethodDefinition","paramnames":["args"]},"vars":{"":null}},"description":"Outputs log at the named level granularity","name":"warn0","longname":"Logger#warn0","kind":"function","memberof":"Logger","scope":"instance","params":[]},{"comment":"/** Synonymous with warn0 */","meta":{"range":[37290,37340],"filename":"Log.js","lineno":1018,"columnno":4,"path":"/build/src","code":{"id":"astnode100005307","name":"Logger#warn","type":"MethodDefinition","paramnames":["args"]},"vars":{"":null}},"description":"Synonymous with warn0","name":"warn","longname":"Logger#warn","kind":"function","memberof":"Logger","scope":"instance","params":[]},{"comment":"/** Used to output a log related to an error. */","meta":{"range":[37398,37460],"filename":"Log.js","lineno":1022,"columnno":4,"path":"/build/src","code":{"id":"astnode100005320","name":"Logger#error","type":"MethodDefinition","paramnames":["args"]},"vars":{"":null}},"description":"Used to output a log related to an error.","name":"error","longname":"Logger#error","kind":"function","memberof":"Logger","scope":"instance","params":[]},{"comment":"/** Used to output a log related to an exception.*/","meta":{"range":[37521,37591],"filename":"Log.js","lineno":1026,"columnno":4,"path":"/build/src","code":{"id":"astnode100005334","name":"Logger#exception","type":"MethodDefinition","paramnames":["args"]},"vars":{"":null}},"description":"Used to output a log related to an exception.","name":"exception","longname":"Logger#exception","kind":"function","memberof":"Logger","scope":"instance","params":[]},{"comment":"/** Used to output a log related to non-recoverable crash.*/","meta":{"range":[37661,37723],"filename":"Log.js","lineno":1030,"columnno":4,"path":"/build/src","code":{"id":"astnode100005348","name":"Logger#fatal","type":"MethodDefinition","paramnames":["args"]},"vars":{"":null}},"description":"Used to output a log related to non-recoverable crash.","name":"fatal","longname":"Logger#fatal","kind":"function","memberof":"Logger","scope":"instance","params":[]},{"comment":"/** alias for fatal */","meta":{"range":[37755,37806],"filename":"Log.js","lineno":1034,"columnno":4,"path":"/build/src","code":{"id":"astnode100005362","name":"Logger#crash","type":"MethodDefinition","paramnames":["args"]},"vars":{"":null}},"description":"alias for fatal","name":"crash","longname":"Logger#crash","kind":"function","memberof":"Logger","scope":"instance","params":[]},{"comment":"/**\n* Declares the start of a contextual group of related log statements.\n* In the ConsoleWriter, Log statements following a group declaration appear slightly indented so as to form\n* a visually grouped collection.  The group block is preceded by a label tag announcing the name of the group.\n*\n* Other Writer implementations may handle `group` blocks in different ways.  Interactive log clients may support\n* collapsible sections.\n*\n* Groups are concluded with `groupEnd` statments.\n*\n* Groups initiated when another group is active appear nested within the former group.\n*\n* @param name\n*/","meta":{"range":[38472,38672],"filename":"Log.js","lineno":1051,"columnno":4,"path":"/build/src","code":{"id":"astnode100005375","name":"Logger#group","type":"MethodDefinition","paramnames":["name"]},"vars":{"":null}},"description":"Declares the start of a contextual group of related log statements.\nIn the ConsoleWriter, Log statements following a group declaration appear slightly indented so as to form\na visually grouped collection.  The group block is preceded by a label tag announcing the name of the group.\n\nOther Writer implementations may handle `group` blocks in different ways.  Interactive log clients may support\ncollapsible sections.\n\nGroups are concluded with `groupEnd` statments.\n\nGroups initiated when another group is active appear nested within the former group.","params":[{"name":"name"}],"name":"group","longname":"Logger#group","kind":"function","memberof":"Logger","scope":"instance"},{"comment":"/**\n* Marks the end of the current group.\n*/","meta":{"range":[38736,38941],"filename":"Log.js","lineno":1061,"columnno":4,"path":"/build/src","code":{"id":"astnode100005415","name":"Logger#groupEnd","type":"MethodDefinition","paramnames":[]},"vars":{"":null}},"description":"Marks the end of the current group.","name":"groupEnd","longname":"Logger#groupEnd","kind":"function","memberof":"Logger","scope":"instance","params":[]},{"comment":"//------------------------------------\n/*\n* Applies color for the ColorWriter.\n* If an array is used, the first element represents the color of the foreground, and the second of the background.\n* If a string is given, it is used as the foreground color.\n*\n* Colors may be a direct ANSI number (8-bit extended), a three digit hex ('#ABC'), six-digit hex ('#123456'),\n* or 'rgb()' statement.\n*\n* Undefined or '' entries are no-ops.\n*\n* @param strOrArray\n* @returns {string}\n*/","meta":{"range":[39456,39941],"filename":"Log.js","lineno":1084,"columnno":0,"path":"/build/src","code":{"id":"astnode100005461","name":"applyColor","type":"FunctionDeclaration","paramnames":["strOrArray"]},"vars":{"strOrArray":"applyColor~strOrArray","sFg":"applyColor~sFg","sBg":"applyColor~sBg","out":"applyColor~out","code":"applyColor~code"}},"undocumented":true,"name":"applyColor","longname":"applyColor","kind":"function","scope":"global","params":[]},{"comment":"// Used by applyColor","meta":{"range":[39964,41265],"filename":"Log.js","lineno":1104,"columnno":0,"path":"/build/src","code":{"id":"astnode100005542","name":"parseColor","type":"FunctionDeclaration","paramnames":["str"]},"vars":{"s":"parseColor~s","e":"parseColor~e","rgb":"parseColor~rgb","r":"parseColor~r","g":"parseColor~g","b":"parseColor~b","str":"parseColor~str","i":"parseColor~i","v":"parseColor~v","n":"parseColor~n"}},"undocumented":true,"name":"parseColor","longname":"parseColor","kind":"function","scope":"global","params":[]},{"comment":"// TODO: Handle the first 16 colors (primary, bright)\n// Used by applyColor","meta":{"range":[41342,42065],"filename":"Log.js","lineno":1147,"columnno":0,"path":"/build/src","code":{"id":"astnode100005804","name":"rgb2ansiCode","type":"FunctionDeclaration","paramnames":["str"]},"vars":{"rgb":"rgb2ansiCode~rgb","R":"rgb2ansiCode~R","G":"rgb2ansiCode~G","B":"rgb2ansiCode~B","code":"rgb2ansiCode~code","g":"rgb2ansiCode~g"}},"undocumented":true,"name":"rgb2ansiCode","longname":"rgb2ansiCode","kind":"function","scope":"global","params":[]},{"comment":"// -----------------------","meta":{"range":[42093,42481],"filename":"Log.js","lineno":1171,"columnno":0,"path":"/build/src","code":{"id":"astnode100005938","name":"expandObject","type":"FunctionDeclaration","paramnames":["key","value"]}},"undocumented":true,"name":"expandObject","longname":"expandObject","kind":"function","scope":"global","params":[]},{"comment":"","meta":{"range":[1648,2338],"filename":"SourceMap.js","lineno":44,"columnno":0,"path":"/build/src","code":{"id":"astnode100006249","name":"getSmxInfo","type":"FunctionDeclaration","paramnames":[]},"vars":{"gsmx":"getSmxInfo~gsmx","smxInfo":"getSmxInfo~smxInfo","oneTime":"getSmxInfo~oneTime"}},"undocumented":true,"name":"getSmxInfo","longname":"getSmxInfo","kind":"function","scope":"global","params":[]},{"comment":"","meta":{"range":[2345,2395],"filename":"SourceMap.js","lineno":66,"columnno":6,"path":"/build/src","code":{"id":"astnode100006307","name":"smCodec","type":"CallExpression","value":""}},"undocumented":true,"name":"smCodec","longname":"smCodec","kind":"constant","scope":"global","params":[]},{"comment":"","meta":{"range":[2403,2444],"filename":"SourceMap.js","lineno":67,"columnno":6,"path":"/build/src","code":{"id":"astnode100006315","name":"base64","type":"CallExpression","value":""}},"undocumented":true,"name":"base64","longname":"base64","kind":"constant","scope":"global","params":[]},{"comment":"/**\n* Read the target (.js) file and find the //# sourceMappingURL= tag\n* then, either decode the date or read the referenced map file depending upon url type\n*\n* Record this as the mapData for this file path for later lookup.\n* Note that in 'Sniff' the first part (making a mapData table) is done as a post-build tool activity\n* and the resulting JSON is read in so we have a preconstructed source map table at the start.\n*\n* @param filePath Path of the file (note: full path, not just the name)\n*/","meta":{"range":[2955,4250],"filename":"SourceMap.js","lineno":78,"columnno":0,"path":"/build/src","code":{"id":"astnode100006322","name":"readMapData","type":"FunctionDeclaration","paramnames":["filePath"]},"vars":{"mapData":"readMapData~mapData","contents":"readMapData~contents","tag":"readMapData~tag","n":"readMapData~n","snip":"readMapData~snip","b64tag":"readMapData~b64tag","dn":"readMapData~dn","b64":"readMapData~b64","mapText":"readMapData~mapText","mapPath":"readMapData~mapPath"}},"description":"Read the target (.js) file and find the //# sourceMappingURL= tag\nthen, either decode the date or read the referenced map file depending upon url type\n\nRecord this as the mapData for this file path for later lookup.\nNote that in 'Sniff' the first part (making a mapData table) is done as a post-build tool activity\nand the resulting JSON is read in so we have a preconstructed source map table at the start.","params":[{"description":"Path of the file (note: full path, not just the name)","name":"filePath"}],"name":"readMapData","longname":"readMapData","kind":"function","scope":"global"},{"comment":"/**\n* From the already parsed FuncFileLine data from StackLineParser,\n* find the referenced source map data and decode it to find the corresponding\n* source file and line values.  Update the FFL object in place.\n* Resulting FFL will also contain the source file path.\n*\n* @param ffl FuncFileLine object that is modified with source map information and returned\n* @return Modified FFL is also returned\n*/","meta":{"range":[4663,6585],"filename":"SourceMap.js","lineno":122,"columnno":0,"path":"/build/src","code":{"id":"astnode100006482","name":"getSourceMap","type":"FunctionDeclaration","paramnames":["ffl"]},"vars":{"smxInfo":"getSourceMap~smxInfo","mapData":"getSourceMap~mapData","decoded":"getSourceMap~decoded","lc":"getSourceMap~lc","line":"getSourceMap~line","decEntryArr":"getSourceMap~decEntryArr","skipped":"getSourceMap~skipped","decEntry":"getSourceMap~decEntry","srcindex":"getSourceMap~srcindex","orgFile":"getSourceMap~orgFile","rootPath":"getSourceMap~rootPath","ffl.sourcePath":"ffl.sourcePath","orgLine":"getSourceMap~orgLine","ffl.file":"ffl.file","ffl.column":"ffl.column","ffl.line":"ffl.line"}},"description":"From the already parsed FuncFileLine data from StackLineParser,\nfind the referenced source map data and decode it to find the corresponding\nsource file and line values.  Update the FFL object in place.\nResulting FFL will also contain the source file path.","params":[{"description":"FuncFileLine object that is modified with source map information and returned","name":"ffl"}],"returns":[{"description":"Modified FFL is also returned"}],"name":"getSourceMap","longname":"getSourceMap","kind":"function","scope":"global"},{"comment":"","meta":{"range":[140,176],"filename":"StackLineParser.js","lineno":4,"columnno":6,"path":"/build/src","code":{"id":"astnode100006760","name":"SourceMap_1","type":"CallExpression","value":""}},"undocumented":true,"name":"SourceMap_1","longname":"SourceMap_1","kind":"constant","scope":"global","params":[]},{"comment":"","meta":{"range":[178,279],"filename":"StackLineParser.js","lineno":5,"columnno":0,"path":"/build/src","code":{"id":"astnode100006765","name":"FuncFileLine","type":"ClassDeclaration","paramnames":[]}},"undocumented":true,"name":"FuncFileLine","longname":"FuncFileLine","kind":"class","scope":"global"},{"comment":"","meta":{"range":[203,277],"filename":"StackLineParser.js","lineno":6,"columnno":4,"path":"/build/src","code":{"id":"astnode100006768","name":"FuncFileLine","type":"MethodDefinition","paramnames":[]},"vars":{"":null}},"undocumented":true,"name":"FuncFileLine","longname":"FuncFileLine","kind":"class","scope":"global","params":[]},{"comment":"","meta":{"range":[317,2803],"filename":"StackLineParser.js","lineno":11,"columnno":0,"path":"/build/src","code":{"id":"astnode100006784","name":"StackLineParser","type":"ClassDeclaration","paramnames":[]}},"undocumented":true,"name":"StackLineParser","longname":"StackLineParser","kind":"class","scope":"global"},{"comment":"","meta":{"range":[345,1026],"filename":"StackLineParser.js","lineno":12,"columnno":4,"path":"/build/src","code":{"id":"astnode100006787","name":"StackLineParser#getFuncFileLine","type":"MethodDefinition","paramnames":[]},"vars":{"":null}},"undocumented":true,"name":"getFuncFileLine","longname":"StackLineParser#getFuncFileLine","kind":"function","memberof":"StackLineParser","scope":"instance","params":[]},{"comment":"","meta":{"range":[1031,2801],"filename":"StackLineParser.js","lineno":30,"columnno":4,"path":"/build/src","code":{"id":"astnode100006897","name":"StackLineParser#parseLine","type":"MethodDefinition","paramnames":["ln"]},"vars":{"":null}},"undocumented":true,"name":"parseLine","longname":"StackLineParser#parseLine","kind":"function","memberof":"StackLineParser","scope":"instance","params":[]},{"comment":"","meta":{"range":[83,111],"filename":"start.js","lineno":3,"columnno":6,"path":"/build","code":{"id":"astnode100007168","name":"Log_1","type":"CallExpression","value":""}},"undocumented":true,"name":"Log_1","longname":"Log_1","kind":"constant","scope":"global","params":[]},{"comment":"","meta":{"range":[1274,1308],"filename":"start.js","lineno":39,"columnno":6,"path":"/build","code":{"id":"astnode100007182","name":"Log","type":"CallExpression","value":""}},"undocumented":true,"name":"Log","longname":"Log","kind":"constant","scope":"global","params":[]},{"comment":"","meta":{"range":[1751,4356],"filename":"start.js","lineno":54,"columnno":0,"path":"/build","code":{"id":"astnode100007253","name":"logTest","type":"FunctionDeclaration","paramnames":[]},"vars":{"":null,"multiLine":"logTest~multiLine"}},"undocumented":true,"name":"logTest","longname":"logTest","kind":"function","scope":"global","params":[]},{"comment":"","meta":{"range":[4466,4700],"filename":"start.js","lineno":123,"columnno":0,"path":"/build","code":{"id":"astnode100007625","name":"a","type":"FunctionDeclaration","paramnames":[]},"vars":{"a":"a~a","x":"a~x"}},"undocumented":true,"name":"a","longname":"a","kind":"function","scope":"global","params":[]},{"comment":"","meta":{"range":[4701,4733],"filename":"start.js","lineno":134,"columnno":0,"path":"/build","code":{"id":"astnode100007661","name":"b","type":"FunctionDeclaration","paramnames":[]}},"undocumented":true,"name":"b","longname":"b","kind":"function","scope":"global","params":[]},{"comment":"","meta":{"range":[4734,4766],"filename":"start.js","lineno":137,"columnno":0,"path":"/build","code":{"id":"astnode100007667","name":"c","type":"FunctionDeclaration","paramnames":[]}},"undocumented":true,"name":"c","longname":"c","kind":"function","scope":"global","params":[]},{"comment":"","meta":{"range":[4767,4799],"filename":"start.js","lineno":140,"columnno":0,"path":"/build","code":{"id":"astnode100007673","name":"d","type":"FunctionDeclaration","paramnames":[]}},"undocumented":true,"name":"d","longname":"d","kind":"function","scope":"global","params":[]},{"comment":"","meta":{"range":[4800,4832],"filename":"start.js","lineno":143,"columnno":0,"path":"/build","code":{"id":"astnode100007679","name":"e","type":"FunctionDeclaration","paramnames":[]}},"undocumented":true,"name":"e","longname":"e","kind":"function","scope":"global","params":[]}]}